MANIFEST.in
README.md
setup.cfg
setup.py
devlog/__init__.py
devlog/devlog.py
devlog.egg-info/PKG-INFO
devlog.egg-info/SOURCES.txt
devlog.egg-info/dependency_links.txt
devlog.egg-info/entry_points.txt
devlog.egg-info/top_level.txt