Metadata-Version: 1.2
Name: devlog
Version: 1.0.1
Summary: A simple command line developer log
Home-page: https://www.github.com/kachamukabe/devlog
Author: Kacha Mukabe
Author-email: kmukabe@gmail.com
License: MIT
Keywords: development blogging
Platform: UNKNOWN
Requires-Python: >=3
